{
  "project_info": {
    "project_number": "288094639616",
    "firebase_url": "https://survey-mayor.firebaseio.com",
    "project_id": "survey-mayor",
    "storage_bucket": "survey-mayor.appspot.com"
  },
  "client": [
    {
      "client_info": {
        "mobilesdk_app_id": "1:288094639616:android:9a012c6b19c78ddd436ae5",
        "android_client_info": {
          "package_name": "com.example.surveymayor"
        }
      },
      "oauth_client": [
        {
          "client_id": "288094639616-v595de1doqkbe6q57jrgj16g2kv7tg2b.apps.googleusercontent.com",
          "client_type": 3
        }
      ],
      "api_key": [
        {
          "current_key": "AIzaSyDOKok1iZkpp-UdfaaZkWaV5l3EWIkhYoE"
        }
      ],
      "services": {
        "appinvite_service": {
          "other_platform_oauth_client": [
            {
              "client_id": "288094639616-v595de1doqkbe6q57jrgj16g2kv7tg2b.apps.googleusercontent.com",
              "client_type": 3
            }
          ]
        }
      }
    }
  ],
  "configuration_version": "1"
}